pypedrive_async/__init__.py
pypedrive_async/api.py
pypedrive_async/objects.py
pypedrive_async-0.2.7.dist-info/METADATA
pypedrive_async-0.2.7.dist-info/WHEEL
pypedrive_async-0.2.7.dist-info/top_level.txt
pypedrive_async-0.2.7.dist-info/RECORD
